README.rst
setup.py
Flask_Auth_Client.egg-info/PKG-INFO
Flask_Auth_Client.egg-info/SOURCES.txt
Flask_Auth_Client.egg-info/dependency_links.txt
Flask_Auth_Client.egg-info/requires.txt
Flask_Auth_Client.egg-info/top_level.txt
flask_auth_client/__init__.py