Metadata-Version: 1.1
Name: Flask-Auth-Client
Version: 0.0.2
Summary: API client for flask extension
Home-page: UNKNOWN
Author: codeif
Author-email: me@codeif.com
License: MIT
Platform: UNKNOWN
Classifier: Programming Language :: Python :: 3
